my_py_utils/__init__.py
my_py_utils/my_py_utils.py
my_py_utils-0.4.3.7.2.dist-info/METADATA
my_py_utils-0.4.3.7.2.dist-info/RECORD
my_py_utils-0.4.3.7.2.dist-info/WHEEL
my_py_utils-0.4.3.7.2.dist-info/top_level.txt
